limes/__init__.py
limes/__main__.py
limes/limes.py
limes/res/__init__.py
limes/res/strings.py
limes/tools/__init__.py
limes/tools/qol.py
limes_common/__init__.py
limes_common/config.py
limes_common/exceptions.py
limes_common/utils.py
limes_common/connections/__init__.py
limes_common/connections/http.py
limes_common/connections/ssh.py
limes_common/connections/statics/__init__.py
limes_common/connections/statics/eLab.py
limes_common/connections/statics/server.py
limes_common/models/__init__.py
limes_common/models/basic.py
limes_common/models/elab.py
limes_common/models/http.py
limes_common/models/provider.py
limes_common/models/server.py
limes_common/models/ssh.py
limes_inventory-0.4.1.dist-info/LICENSE
limes_inventory-0.4.1.dist-info/METADATA
limes_inventory-0.4.1.dist-info/WHEEL
limes_inventory-0.4.1.dist-info/entry_points.txt
limes_inventory-0.4.1.dist-info/top_level.txt
limes_inventory-0.4.1.dist-info/RECORD
